
{
  "header": {
    "reportVersion": 1,
    "event": "Allocation failed - JavaScript heap out of memory",
    "trigger": "FatalError",
    "filename": "report.20200120.154905.39040.0.001.json",
    "dumpEventTime": "2020-01-20T15:49:05Z",
    "dumpEventTimeStamp": "1579531745348",
    "processId": 39040,
    "cwd": "/Users/hadi/app/fbw26/live-coding/20-01",
    "commandLine": [
      "/usr/local/Cellar/node/12.12.0/bin/node",
      "index.js"
    ],
    "nodejsVersion": "v12.12.0",
    "wordSize": 64,
    "arch": "x64",
    "platform": "darwin",
    "componentVersions": {
      "node": "12.12.0",
      "v8": "7.7.299.13-node.12",
      "uv": "1.32.0",
      "zlib": "1.2.11",
      "brotli": "1.0.7",
      "ares": "1.15.0",
      "modules": "72",
      "nghttp2": "1.39.2",
      "napi": "5",
      "llhttp": "1.1.4",
      "http_parser": "2.8.0",
      "openssl": "1.1.1d",
      "cldr": "35.1",
      "icu": "64.2",
      "tz": "2019a",
      "unicode": "12.1"
    },
    "release": {
      "name": "node",
      "headersUrl": "https://nodejs.org/download/release/v12.12.0/node-v12.12.0-headers.tar.gz",
      "sourceUrl": "https://nodejs.org/download/release/v12.12.0/node-v12.12.0.tar.gz"
    },
    "osName": "Darwin",
    "osRelease": "19.2.0",
    "osVersion": "Darwin Kernel Version 19.2.0: Sat Nov  9 03:47:04 PST 2019; root:xnu-6153.61.1~20/RELEASE_X86_64",
    "osMachine": "x86_64",
    "cpus": [
      {
        "model": "Intel(R) Core(TM) i5-8257U CPU @ 1.40GHz",
        "speed": 1400,
        "user": 20885180,
        "nice": 0,
        "sys": 13697550,
        "idle": 257366440,
        "irq": 0
      },
      {
        "model": "Intel(R) Core(TM) i5-8257U CPU @ 1.40GHz",
        "speed": 1400,
        "user": 1086630,
        "nice": 0,
        "sys": 982930,
        "idle": 289816700,
        "irq": 0
      },
      {
        "model": "Intel(R) Core(TM) i5-8257U CPU @ 1.40GHz",
        "speed": 1400,
        "user": 20894430,
        "nice": 0,
        "sys": 8991320,
        "idle": 262004060,
        "irq": 0
      },
      {
        "model": "Intel(R) Core(TM) i5-8257U CPU @ 1.40GHz",
        "speed": 1400,
        "user": 879450,
        "nice": 0,
        "sys": 780680,
        "idle": 290225970,
        "irq": 0
      },
      {
        "model": "Intel(R) Core(TM) i5-8257U CPU @ 1.40GHz",
        "speed": 1400,
        "user": 14642290,
        "nice": 0,
        "sys": 6517720,
        "idle": 270729620,
        "irq": 0
      },
      {
        "model": "Intel(R) Core(TM) i5-8257U CPU @ 1.40GHz",
        "speed": 1400,
        "user": 849490,
        "nice": 0,
        "sys": 689380,
        "idle": 290347060,
        "irq": 0
      },
      {
        "model": "Intel(R) Core(TM) i5-8257U CPU @ 1.40GHz",
        "speed": 1400,
        "user": 10704040,
        "nice": 0,
        "sys": 4593580,
        "idle": 276591830,
        "irq": 0
      },
      {
        "model": "Intel(R) Core(TM) i5-8257U CPU @ 1.40GHz",
        "speed": 1400,
        "user": 821980,
        "nice": 0,
        "sys": 605090,
        "idle": 290458690,
        "irq": 0
      }
    ],
    "networkInterfaces": [
      {
        "name": "lo0",
        "internal": true,
        "mac": "00:00:00:00:00:00",
        "address": "127.0.0.1",
        "netmask": "255.0.0.0",
        "family": "IPv4"
      },
      {
        "name": "lo0",
        "internal": true,
        "mac": "00:00:00:00:00:00",
        "address": "::1",
        "netmask": "ffff:ffff:ffff:ffff:ffff:ffff:ffff:ffff",
        "family": "IPv6",
        "scopeid": 0
      },
      {
        "name": "lo0",
        "internal": true,
        "mac": "00:00:00:00:00:00",
        "address": "fe80::1",
        "netmask": "ffff:ffff:ffff:ffff::",
        "family": "IPv6",
        "scopeid": 1
      },
      {
        "name": "en3",
        "internal": false,
        "mac": "ac:de:48:00:11:22",
        "address": "fe80::aede:48ff:fe00:1122",
        "netmask": "ffff:ffff:ffff:ffff::",
        "family": "IPv6",
        "scopeid": 4
      },
      {
        "name": "en0",
        "internal": false,
        "mac": "a4:83:e7:64:77:7c",
        "address": "fe80::10a3:7015:b4c8:7797",
        "netmask": "ffff:ffff:ffff:ffff::",
        "family": "IPv6",
        "scopeid": 6
      },
      {
        "name": "en0",
        "internal": false,
        "mac": "a4:83:e7:64:77:7c",
        "address": "172.31.32.175",
        "netmask": "255.255.255.0",
        "family": "IPv4"
      },
      {
        "name": "awdl0",
        "internal": false,
        "mac": "fe:bd:df:33:e8:f1",
        "address": "fe80::fcbd:dfff:fe33:e8f1",
        "netmask": "ffff:ffff:ffff:ffff::",
        "family": "IPv6",
        "scopeid": 11
      },
      {
        "name": "llw0",
        "internal": false,
        "mac": "fe:bd:df:33:e8:f1",
        "address": "fe80::fcbd:dfff:fe33:e8f1",
        "netmask": "ffff:ffff:ffff:ffff::",
        "family": "IPv6",
        "scopeid": 12
      },
      {
        "name": "utun0",
        "internal": false,
        "mac": "00:00:00:00:00:00",
        "address": "fe80::fb97:d4dc:435b:fb77",
        "netmask": "ffff:ffff:ffff:ffff::",
        "family": "IPv6",
        "scopeid": 13
      },
      {
        "name": "utun1",
        "internal": false,
        "mac": "00:00:00:00:00:00",
        "address": "fe80::c8d7:c57d:f62f:107a",
        "netmask": "ffff:ffff:ffff:ffff::",
        "family": "IPv6",
        "scopeid": 14
      },
      {
        "name": "utun2",
        "internal": false,
        "mac": "00:00:00:00:00:00",
        "address": "fe80::71b4:a9b0:de3a:44d0",
        "netmask": "ffff:ffff:ffff:ffff::",
        "family": "IPv6",
        "scopeid": 15
      },
      {
        "name": "utun3",
        "internal": false,
        "mac": "00:00:00:00:00:00",
        "address": "fe80::3f9:34e2:e0d4:a3a0",
        "netmask": "ffff:ffff:ffff:ffff::",
        "family": "IPv6",
        "scopeid": 16
      }
    ],
    "host": "Hadis-MacBook-Pro.local"
  },
  "javascriptStack": {
    "message": "No stack.",
    "stack": [
      "Unavailable."
    ]
  },
  "nativeStack": [
    {
      "pc": "0x00000001001515eb",
      "symbol": "report::TriggerNodeReport(v8::Isolate*, node::Environment*, char const*, char const*, std::__1::basic_string<char, std::__1::char_traits<char>, std::__1::allocator<char> > const&, v8::Local<v8::String>) [/usr/local/Cellar/node/12.12.0/bin/node]"
    },
    {
      "pc": "0x0000000100082067",
      "symbol": "node::OnFatalError(char const*, char const*) [/usr/local/Cellar/node/12.12.0/bin/node]"
    },
    {
      "pc": "0x000000010017461d",
      "symbol": "v8::Utils::ReportOOMFailure(v8::internal::Isolate*, char const*, bool) [/usr/local/Cellar/node/12.12.0/bin/node]"
    },
    {
      "pc": "0x00000001001745c7",
      "symbol": "v8::internal::V8::FatalProcessOutOfMemory(v8::internal::Isolate*, char const*, bool) [/usr/local/Cellar/node/12.12.0/bin/node]"
    },
    {
      "pc": "0x000000010028a569",
      "symbol": "v8::internal::Heap::FatalProcessOutOfMemory(char const*) [/usr/local/Cellar/node/12.12.0/bin/node]"
    },
    {
      "pc": "0x000000010026d839",
      "symbol": "v8::internal::Factory::AllocateRawFixedArray(int, v8::internal::AllocationType) [/usr/local/Cellar/node/12.12.0/bin/node]"
    },
    {
      "pc": "0x000000010026c8d6",
      "symbol": "v8::internal::Factory::NewFixedArrayWithFiller(v8::internal::RootIndex, int, v8::internal::Object, v8::internal::AllocationType) [/usr/local/Cellar/node/12.12.0/bin/node]"
    },
    {
      "pc": "0x0000000100370463",
      "symbol": "v8::internal::(anonymous namespace)::ElementsAccessorBase<v8::internal::(anonymous namespace)::FastPackedSmiElementsAccessor, v8::internal::(anonymous namespace)::ElementsKindTraits<(v8::internal::ElementsKind)0> >::ConvertElementsWithCapacity(v8::internal::Handle<v8::internal::JSObject>, v8::internal::Handle<v8::internal::FixedArrayBase>, v8::internal::ElementsKind, unsigned int, unsigned int, unsigned int) [/usr/local/Cellar/node/12.12.0/bin/node]"
    },
    {
      "pc": "0x000000010036f17a",
      "symbol": "v8::internal::(anonymous namespace)::ElementsAccessorBase<v8::internal::(anonymous namespace)::FastPackedSmiElementsAccessor, v8::internal::(anonymous namespace)::ElementsKindTraits<(v8::internal::ElementsKind)0> >::GrowCapacity(v8::internal::Handle<v8::internal::JSObject>, unsigned int) [/usr/local/Cellar/node/12.12.0/bin/node]"
    },
    {
      "pc": "0x000000010049a532",
      "symbol": "v8::internal::Runtime_GrowArrayElements(int, unsigned long*, v8::internal::Isolate*) [/usr/local/Cellar/node/12.12.0/bin/node]"
    },
    {
      "pc": "0x000000010072e699",
      "symbol": "Builtins_CEntry_Return1_DontSaveFPRegs_ArgvOnStack_NoBuiltinExit [/usr/local/Cellar/node/12.12.0/bin/node]"
    }
  ],
  "javascriptHeap": {
    "totalMemory": 3151949824,
    "totalCommittedMemory": 3119269928,
    "usedMemory": 3116542872,
    "availableMemory": 16989384,
    "memoryLimit": 2197815296,
    "heapSpaces": {
      "read_only_space": {
        "memorySize": 262144,
        "committedMemory": 32568,
        "capacity": 261872,
        "used": 32296,
        "available": 229576
      },
      "new_space": {
        "memorySize": 33554432,
        "committedMemory": 2076304,
        "capacity": 16759808,
        "used": 0,
        "available": 16759808
      },
      "old_space": {
        "memorySize": 2469888,
        "committedMemory": 1975936,
        "capacity": 1513192,
        "used": 1513192,
        "available": 0
      },
      "code_space": {
        "memorySize": 425984,
        "committedMemory": 180672,
        "capacity": 160736,
        "used": 160736,
        "available": 0
      },
      "map_space": {
        "memorySize": 528384,
        "committedMemory": 295456,
        "capacity": 213680,
        "used": 213680,
        "available": 0
      },
      "large_object_space": {
        "memorySize": 2071175168,
        "committedMemory": 2071175168,
        "capacity": 2071137816,
        "used": 2071137816,
        "available": 0
      },
      "code_large_object_space": {
        "memorySize": 49152,
        "committedMemory": 49152,
        "capacity": 3552,
        "used": 3552,
        "available": 0
      },
      "new_large_object_space": {
        "memorySize": 1043484672,
        "committedMemory": 1043484672,
        "capacity": 1043481600,
        "used": 1043481600,
        "available": 0
      }
    }
  },
  "resourceUsage": {
    "userCpuSeconds": 2.07653,
    "kernelCpuSeconds": 0.612161,
    "cpuConsumptionPercent": 134.435,
    "maxRss": 3212459376640,
    "pageFaults": {
      "IORequired": 0,
      "IONotRequired": 770037
    },
    "fsActivity": {
      "reads": 0,
      "writes": 0
    }
  },
  "libuv": [
  ],
  "environmentVariables": {
    "USER": "hadi",
    "COMMAND_MODE": "unix2003",
    "PATH": "/usr/local/bin:/usr/bin:/bin:/usr/sbin:/sbin",
    "LOGNAME": "hadi",
    "SSH_AUTH_SOCK": "/private/tmp/com.apple.launchd.X3WLYsPtY8/Listeners",
    "HOME": "/Users/hadi",
    "SHELL": "/bin/zsh",
    "TMPDIR": "/var/folders/n9/1b2fx7j90hd7g86hjclv_x480000gn/T/",
    "__CF_USER_TEXT_ENCODING": "0x1F5:0x0:0x2",
    "XPC_SERVICE_NAME": "0",
    "XPC_FLAGS": "0x0",
    "OLDPWD": "/Users/hadi/app/fbw26/live-coding",
    "PWD": "/Users/hadi/app/fbw26/live-coding/20-01",
    "SHLVL": "1",
    "TERM_PROGRAM": "vscode",
    "TERM_PROGRAM_VERSION": "1.41.1",
    "LANG": "en_GB.UTF-8",
    "COLORTERM": "truecolor",
    "TERM": "xterm-256color",
    "_": "/usr/local/bin/nodemon"
  },
  "userLimits": {
    "core_file_size_blocks": {
      "soft": 0,
      "hard": "unlimited"
    },
    "data_seg_size_kbytes": {
      "soft": "unlimited",
      "hard": "unlimited"
    },
    "file_size_blocks": {
      "soft": "unlimited",
      "hard": "unlimited"
    },
    "max_locked_memory_bytes": {
      "soft": "unlimited",
      "hard": "unlimited"
    },
    "max_memory_size_kbytes": {
      "soft": "unlimited",
      "hard": "unlimited"
    },
    "open_files": {
      "soft": 10240,
      "hard": "unlimited"
    },
    "stack_size_bytes": {
      "soft": 8388608,
      "hard": 67104768
    },
    "cpu_time_seconds": {
      "soft": "unlimited",
      "hard": "unlimited"
    },
    "max_user_processes": {
      "soft": 1392,
      "hard": 2088
    },
    "virtual_memory_kbytes": {
      "soft": "unlimited",
      "hard": "unlimited"
    }
  },
  "sharedObjects": [
    "/usr/local/Cellar/node/12.12.0/bin/node",
    "/usr/local/opt/icu4c/lib/libicui18n.64.dylib",
    "/usr/local/opt/icu4c/lib/libicuuc.64.dylib",
    "/usr/local/opt/icu4c/lib/libicudata.64.dylib",
    "/System/Library/Frameworks/CoreFoundation.framework/Versions/A/CoreFoundation",
    "/usr/lib/libSystem.B.dylib",
    "/usr/lib/libc++.1.dylib",
    "/usr/lib/system/libcache.dylib",
    "/usr/lib/system/libcommonCrypto.dylib",
    "/usr/lib/system/libcompiler_rt.dylib",
    "/usr/lib/system/libcopyfile.dylib",
    "/usr/lib/system/libcorecrypto.dylib",
    "/usr/lib/system/libdispatch.dylib",
    "/usr/lib/system/libdyld.dylib",
    "/usr/lib/system/libkeymgr.dylib",
    "/usr/lib/system/liblaunch.dylib",
    "/usr/lib/system/libmacho.dylib",
    "/usr/lib/system/libquarantine.dylib",
    "/usr/lib/system/libremovefile.dylib",
    "/usr/lib/system/libsystem_asl.dylib",
    "/usr/lib/system/libsystem_blocks.dylib",
    "/usr/lib/system/libsystem_c.dylib",
    "/usr/lib/system/libsystem_configuration.dylib",
    "/usr/lib/system/libsystem_coreservices.dylib",
    "/usr/lib/system/libsystem_darwin.dylib",
    "/usr/lib/system/libsystem_dnssd.dylib",
    "/usr/lib/system/libsystem_featureflags.dylib",
    "/usr/lib/system/libsystem_info.dylib",
    "/usr/lib/system/libsystem_m.dylib",
    "/usr/lib/system/libsystem_malloc.dylib",
    "/usr/lib/system/libsystem_networkextension.dylib",
    "/usr/lib/system/libsystem_notify.dylib",
    "/usr/lib/system/libsystem_sandbox.dylib",
    "/usr/lib/system/libsystem_secinit.dylib",
    "/usr/lib/system/libsystem_kernel.dylib",
    "/usr/lib/system/libsystem_platform.dylib",
    "/usr/lib/system/libsystem_pthread.dylib",
    "/usr/lib/system/libsystem_symptoms.dylib",
    "/usr/lib/system/libsystem_trace.dylib",
    "/usr/lib/system/libunwind.dylib",
    "/usr/lib/system/libxpc.dylib",
    "/usr/lib/libobjc.A.dylib",
    "/usr/lib/libc++abi.dylib",
    "/usr/lib/libfakelink.dylib",
    "/usr/lib/libDiagnosticMessagesClient.dylib",
    "/usr/lib/libicucore.A.dylib",
    "/usr/lib/libz.1.dylib"
  ]
}